backtrader/__init__.py
backtrader/analyzer.py
backtrader/broker.py
backtrader/cerebro.py
backtrader/comminfo.py
backtrader/dataseries.py
backtrader/errors.py
backtrader/feed.py
backtrader/fillers.py
backtrader/flt.py
backtrader/functions.py
backtrader/indicator.py
backtrader/linebuffer.py
backtrader/lineiterator.py
backtrader/lineroot.py
backtrader/lineseries.py
backtrader/mathsupport.py
backtrader/metabase.py
backtrader/observer.py
backtrader/order.py
backtrader/position.py
backtrader/resamplerfilter.py
backtrader/signal.py
backtrader/sizer.py
backtrader/store.py
backtrader/strategy.py
backtrader/talib.py
backtrader/timer.py
backtrader/trade.py
backtrader/tradingcal.py
backtrader/version.py
backtrader/writer.py
backtrader/analyzers/__init__.py
backtrader/analyzers/annualreturn.py
backtrader/analyzers/calmar.py
backtrader/analyzers/drawdown.py
backtrader/analyzers/leverage.py
backtrader/analyzers/logreturnsrolling.py
backtrader/analyzers/periodstats.py
backtrader/analyzers/positions.py
backtrader/analyzers/pyfolio.py
backtrader/analyzers/returns.py
backtrader/analyzers/sharpe.py
backtrader/analyzers/sqn.py
backtrader/analyzers/timereturn.py
backtrader/analyzers/tradeanalyzer.py
backtrader/analyzers/transactions.py
backtrader/analyzers/vwr.py
backtrader/brokers/__init__.py
backtrader/brokers/bbroker.py
backtrader/brokers/ibbroker.py
backtrader/brokers/oandabroker.py
backtrader/brokers/vcbroker.py
backtrader/btrun/__init__.py
backtrader/btrun/btrun.py
backtrader/commissions/__init__.py
backtrader/feeds/__init__.py
backtrader/feeds/blaze.py
backtrader/feeds/btcsv.py
backtrader/feeds/chainer.py
backtrader/feeds/csvgeneric.py
backtrader/feeds/ibdata.py
backtrader/feeds/influxfeed.py
backtrader/feeds/mt4csv.py
backtrader/feeds/oanda.py
backtrader/feeds/pandafeed.py
backtrader/feeds/quandl.py
backtrader/feeds/rollover.py
backtrader/feeds/sierrachart.py
backtrader/feeds/vcdata.py
backtrader/feeds/vchart.py
backtrader/feeds/vchartcsv.py
backtrader/feeds/vchartfile.py
backtrader2-1.9.76.123.dist-info/LICENSE
backtrader2-1.9.76.123.dist-info/METADATA
backtrader2-1.9.76.123.dist-info/WHEEL
backtrader2-1.9.76.123.dist-info/entry_points.txt
backtrader2-1.9.76.123.dist-info/top_level.txt
backtrader2-1.9.76.123.dist-info/RECORD
